.hgignore
.hgtags
COPYING
HISTORY.rst
README.rst
mercurial_all_paths.py
noxfile.py
setup.py
mercurial_all_paths.egg-info/PKG-INFO
mercurial_all_paths.egg-info/SOURCES.txt
mercurial_all_paths.egg-info/dependency_links.txt
mercurial_all_paths.egg-info/requires.txt
mercurial_all_paths.egg-info/top_level.txt
mercurial_all_paths.egg-info/zip-safe
tests/basic.t
tests/duplicates.t
tests/facing_problems.t
tests/groups-legacy.t
tests/groups-modern.t
tests/ignore_and_prioritize.t
tests/manual/test_missing_meu.sh