Metadata-Version: 2.1
Name: mercurial_all_paths
Version: 1.2.2
Summary: Mercurial allpaths extension
Home-page: https://foss.heptapod.net/mercurial/mercurial-all_paths
Author: Marcin Kasperski
Author-email: Marcin.Kasperski@mekk.waw.pl
License: GNU General Public License v2 (GPLv2)
Keywords: mercurial paths multi extension
Classifier: Development Status :: 4 - Beta
Classifier: Environment :: Console
Classifier: Intended Audience :: Developers
Classifier: License :: DFSG approved
Classifier: Programming Language :: Python :: 2
Classifier: Programming Language :: Python :: 3
Classifier: Operating System :: OS Independent
Classifier: Topic :: Software Development :: Version Control
License-File: COPYING
Requires-Dist: mercurial_extension_utils>=1.5.0
